{
    "id": 93,
    "url": "https://journals.vsu.ru/lic/article/view/3414",
    "title": "Способы выражения модальности в параллельных текстах стандартов (на примере нормативной базы программной инженерии)",
    "date": "2021-06-01 00:00:00",
    "author": "Ю. И. Бутенко",
    "topics": [
        "тексты",
        "стандартов,",
        "модальность,",
        "модальные",
        "глаголы,",
        "лексические",
        "особенности,",
        "анализ",
        "текстов,",
        "степень",
        "долженствования"
    ]
}